lathermail/__init__.py
lathermail/api.py
lathermail/compat.py
lathermail/db.py
lathermail/default_settings.py
lathermail/mail.py
lathermail/representations.py
lathermail/run_all.py
lathermail/smtp.py
lathermail/utils.py
lathermail/validators.py
lathermail/storage/__init__.py
lathermail/storage/alchemy.py
lathermail/storage/mongo.py
lathermail/web/__init__.py
lathermail/web/static/index.html
lathermail/web/static/js/lathermail.js
tests/__init__.py
tests/__main__.py
tests/test_api.py
tests/utils.py
lathermail-0.4.2.dist-info/LICENSE
lathermail-0.4.2.dist-info/METADATA
lathermail-0.4.2.dist-info/WHEEL
lathermail-0.4.2.dist-info/entry_points.txt
lathermail-0.4.2.dist-info/top_level.txt
lathermail-0.4.2.dist-info/RECORD
