Metadata-Version: 2.1
Name: lathermail
Version: 0.4.2
Summary: SMTP Server with API for email testing inspired by mailtrap and maildump
Home-page: https://github.com/reclosedev/lathermail/
Author: Roman Haritonov
Author-email: reclosedev@gmail.com
License: MIT
Platform: UNKNOWN
Classifier: Development Status :: 4 - Beta
Classifier: Environment :: Web Environment
Classifier: License :: OSI Approved :: MIT License
Classifier: Programming Language :: Python :: 2
Classifier: Programming Language :: Python :: 3
Classifier: Programming Language :: Python :: Implementation :: CPython
Classifier: Programming Language :: Python :: Implementation :: PyPy
Classifier: Topic :: Internet :: WWW/HTTP :: WSGI :: Server
Classifier: Topic :: Communications :: Email
Requires-Dist: Flask (==0.10.1)
Requires-Dist: Flask-RESTful (==0.2.12)
Requires-Dist: Flask-PyMongo (==0.3.0)
Requires-Dist: pymongo (==2.7.1)
Requires-Dist: python-dateutil (==2.2)
Requires-Dist: SQLAlchemy (==1.0.9)
Requires-Dist: Flask-SQLAlchemy (==2.1)
Requires-Dist: MarkupSafe (<=1.1.1)
Requires-Dist: Jinja2 (<=2.11.2)
Requires-Dist: itsdangerous (<=1.1.0)
